{"computelibrary": {}, "mxnet": {"com.sdu.didi.psnger": "libflp-native-v2.txt"}, "mdl": {}, "caffe2": {}, "tflite": {"com.MobileTicket": "libxnn.txt", "com.wuba.bangjob": "libtensorflowlite_jni.txt", "com.yek.android.kfc.activitys": "libtensorflowlite_jni.txt", "com.sdu.didi.psnger": "libtensorflowlite_c.txt", "com.xiaomi.smarthome": "libSNPE.txt", "com.wuba": "libtensorflowlite_jni.txt", "com.anjuke.android.app": "libtensorflowlite_jni.txt", "com.zhaopin.social": "libfuai.txt", "com.sankuai.meituan.takeoutnew": "libtensorflowlite_jni.txt"}, "cnndroid": {}, "dl4j": {}, "paddleLite": {"com.soufun.app": "libpaddle_light_api_shared.txt", "com.jx.cmcc.ict.ibelieve": "libpaddle_light_api_shared.txt"}, "dlib": {}, "mace": {}, "featherCNN": {}, "caffe": {"com.alpha.lagouapk": "libFaceSDK.txt", "com.lietou.mishu": "libtoyger.txt", "com.homelink.android": "libcvfinance_api_liveness_standard.txt", "cn.j.hers": "libst_mobile.txt", "com.wjkj.loosrun": "libtoyger.txt"}, "ncnn": {"com.sdu.didi.gui": "libqqface.txt", "com.sinovatech.unicom.ui": "libdetectionAndRecognition.txt", "com.kingpoint.gmcchh": "libMgFaceLab.txt", "com.sdu.didi.psnger": "libDetect.txt", "com.dianping.v1": "libfaceliveness.txt", "com.jingdong.pdj": "libjdbankcard.txt"}, "mnn": {"com.taobao.mobile.dipei": "libMNN.txt", "com.cainiao.wireless": "libMNN.txt", "me.ele": "libMNN.txt", "com.wlqq4consignor": "libAMapSDK_NAVI_v7_8_0.txt", "com.sankuai.meituan.takeoutnew": "libmodel_vad_wakeup.txt", "com.hpbr.bosszhipin": "libAMapSDK_NAVI_v7_8_0.txt"}, "tengine": {}, "tensorflow": {}, "DNNLibrary": {}, "pytorchmobile": {"com.soufun.app": "libpaddle_light_api_shared.txt", "com.jx.cmcc.ict.ibelieve": "libpaddle_light_api_shared.txt"}, "snpe": {"com.xiaomi.smarthome": "libSNPE.txt"}, "xnn": {}}