{"computelibrary": {}, "mxnet": {"com.didiglobal.passenger": "libflp-native.txt"}, "mdl": {}, "caffe2": {"com.instagram.android": "libgraphicsengine-arengineservices-igeffectservicehost-native.txt"}, "tflite": {"com.style.sticker": "libtensorflowlite_jni.txt", "com.ubercab.eats": "libtensorflowlite_jni.txt", "com.offerup": "libtensorflowlite_jni.txt", "com.marsvard.stickermakerforwhatsapp": "libtensorflowlite_jni.txt", "com.brubank": "libtflite.txt", "com.grability.rappi": "libtensorflowlite_jni.txt", "photo.editor.photoeditor.photoeditorpro": "libtensorflowlite_jni.txt", "com.face.aging.face.truth": "libface_detector_v2_jni.txt", "us.zoom.videomeetings": "libtensorflowlite_jni.txt", "com.afterpaymobile.us": "libbarhopper_v2.txt", "com.amazon.mShop.android.shopping": "libtensorflowlite_jni.txt", "com.tranzmate": "libbarhopper_v2.txt", "com.phonevalley.progressive": "libtensorflowlite_jni.txt", "com.lyrebirdstudio.cartoon": "libface_detector_v2_jni.txt", "com.groupon": "libtensorflowlite_jni.txt", "hint.horoscope.astrology": "libtensorflowlite_jni.txt", "com.movilred.subscriber": "libface_detector_v2_jni.txt", "com.zhiliaoapp.musically": "libtensorflowlite_jni.txt", "com.mobilenik.laanonimaplus": "libtensorflowlite_jni.txt", "pdf.tap.scanner": "libtensorflowlite_jni.txt", "com.hp.printercontrol": "libtensorflowlite_jni.txt", "com.onedebit.chime": "libmlkitcommonpipeline.txt", "com.altrigit.qrscanner": "libbarhopper_v2.txt", "com.target.ui": "libbarhopper_v2.txt", "com.ubercab.driver": "libtensorflowlite_jni.txt", "io.faceapp": "libtensorflowlite_jni.txt", "com.linecorp.b612.android": "libtensorflowlite_c.txt", "com.camvision.qrcode.barcode.reader": "libbarhopper_v2.txt", "com.nike.omega": "libtensorflowlite_jni.txt", "com.ubercab": "libtensorflowlite_jni.txt", "com.pdftechnologies.pdfreaderpro": "libtensorflowlite_jni.txt", "com.google.android.apps.translate": "libtranslate.txt", "com.truecaller": "libtranslate_jni.txt", "com.cisco.webex.meetings": "libPsyML4TFLite.txt", "com.wabi.customer": "libbarhopper_v2.txt", "com.google.android.apps.messaging": "libtask_text_jni.txt", "com.snowcorp.vita": "libtensorflowlite_c.txt", "com.doordash.driverapp": "libbarhopper_v2.txt", "com.zellepay.zelle": "libbarhopper_v2.txt", "me.lyft.android": "libtensorflowlite_jni.txt", "com.alibaba.intl.android.apps.poseidon": "libxnn.txt", "com.dd.doordash": "libtensorflowlite_jni.txt", "com.emoji.coolkeyboard": "librnn_dict.txt", "com.usablenet.mobile.walgreen": "libface_detector_v2_jni.txt", "co.brainly": "libbarhopper_v2.txt", "com.davivienda.daviplataapp": "libbarhopper_v2.txt", "com.microsoft.office.officehubrow": "libtensorflowlite_jni.txt", "com.google.android.apps.authenticator2": "libbarhopper_v2.txt"}, "cnndroid": {}, "dl4j": {}, "paddleLite": {}, "dlib": {"online.cashemall.app": "libPhoenixAndroid.txt", "com.bitso.wallet": "libPhoenixAndroid.txt", "com.tunubi.wallet": "libFPhi.Extractor.txt", "com.paypal.android.p2pmobile": "libd2dd42.txt", "com.instacart.client": "libscanditsdk-android-5.15.0.txt", "com.todo1.mobile": "libscanditsdk-android-5.7.2.txt", "com.grability.rappi": "libPhoenixAndroid.txt", "com.davivienda.daviplataapp": "libPhoenixAndroid.txt"}, "mace": {"com.snapchat.android": "libcamplat+.b9203d471b1f0c5a9fdb4ae2fc6a046f96cdf2e0.txt", "co.triller.droid": "libcamplat+.9baccecb3fa3922f639bbcaabc5c7d499e78e855.txt"}, "featherCNN": {}, "caffe": {"com.linecorp.b612.android": "libst_mobile.txt", "com.snowcorp.vita": "libst_mobile.txt", "me.zepeto.main": "libst_mobile.txt", "com.adobe.reader": "libopencv_java3.txt", "ar.com.bancoprovincia.CuentaDNI": "libopencv_java3.txt", "hint.horoscope.astrology": "libopencv_java3.txt", "com.snowcorp.stickerly.android": "libst_mobile.txt", "pdf.tap.scanner": "libopencv_java4.txt"}, "ncnn": {"com.intsig.camscanner": "libncnn.txt", "com.pinterest": "libMFEMakeupKit.txt", "videoslideshow.photoedit.videocutter": "libRtFacialOutline.txt", "com.didiglobal.passenger": "libaoe_ifx.txt"}, "mnn": {"com.intsig.camscanner": "libMNN.txt", "com.alibaba.intl.android.apps.poseidon": "libMNN.txt", "com.picsart.studio": "libpilibs.txt", "com.alibaba.aliexpresshd": "libMNN.txt"}, "tengine": {}, "tensorflow": {"com.google.android.apps.messaging": "libhobbes_jni.txt", "com.adobe.reader": "libopencv_java3.txt", "ar.com.bancoprovincia.CuentaDNI": "libopencv_java3.txt", "hint.horoscope.astrology": "libopencv_java3.txt", "pdf.tap.scanner": "libopencv_java4.txt", "com.bitstrips.imoji": "libtensorflow_inference.txt"}, "DNNLibrary": {}, "pytorchmobile": {"com.google.android.apps.messaging": "libhobbes_jni.txt", "com.chase.sig.android": "libn.txt"}, "snpe": {}, "xnn": {}}